setup.py
pytest_erp.egg-info/PKG-INFO
pytest_erp.egg-info/SOURCES.txt
pytest_erp.egg-info/dependency_links.txt
pytest_erp.egg-info/entry_points.txt
pytest_erp.egg-info/requires.txt
pytest_erp.egg-info/top_level.txt
pytest_plugin/__init__.py
pytest_plugin/custom_exceptions.py
pytest_plugin/ext_fixtures_behaviour.py
pytest_plugin/logger_extension.py
pytest_plugin/mapping_fixture_action.py
pytest_plugin/pytest_erp_plugin.py
pytest_plugin/rest_erp_client.py