Metadata-Version: 1.0
Name: pytest-erp
Version: 0.0.0
Summary: py.test plugin to send test info to report portal dynamically
Home-page: UNKNOWN
Author: UNKNOWN
Author-email: UNKNOWN
License: UNKNOWN
Platform: UNKNOWN
